mkdocs_translate/__init__.py
mkdocs_translate/__main__.py
mkdocs_translate/cli.py
mkdocs_translate/config.yml
mkdocs_translate/requirements.txt
mkdocs_translate/translate.py
mkdocs_translate-0.4.0.dist-info/LICENSE.md
mkdocs_translate-0.4.0.dist-info/METADATA
mkdocs_translate-0.4.0.dist-info/WHEEL
mkdocs_translate-0.4.0.dist-info/entry_points.txt
mkdocs_translate-0.4.0.dist-info/top_level.txt
mkdocs_translate-0.4.0.dist-info/RECORD
