Metadata-Version: 2.1
Name: mkdocs-translate
Version: 0.4.0
Summary: Translate from sphinx-build to mkdocs-material compatible markdown
Author-email: Jody Garnett <jody.garnett@gmail.com>
License: MIT-License
Project-URL: Homepage, https://jodygarnett.github.io/translate/
Project-URL: Documentation, https://jodygarnett.github.io/translate/setup/
Project-URL: Repository, https://github.com/jodygarnett/translate.git
Project-URL: Changelog, https://github.com/jodygarnett/translate/blob/main/CHANGES
Keywords: mkdocs,markdown,pandoc,sphinx-build,sphinx,rst,reStructuredText,translate
Classifier: Development Status :: 4 - Beta
Classifier: Topic :: Utilities
Classifier: Environment :: Console
Classifier: Programming Language :: Python :: 3
Classifier: License :: OSI Approved :: MIT License
Requires-Python: >=3.9
License-File: LICENSE.md
Requires-Dist: pyyaml
Requires-Dist: requests
Requires-Dist: typer
Requires-Dist: deepl
